Workbook

Sheet Monthly Spending Template
B1: MONTHLY BUDGET TEMPLATE
B5: Total Income | D5: Total Spent | F5: Leftover | H5: Savings Rate | J5: Bills Paid | M5: Budget Split | N5: 50/30/20 | O5: 50/30/20 | Q5: Spending Breakdown | U5: Budgeted | V5: Actual
B6: =SUM(IncomeTbl_MonthlySpendingTemplate57[Amount]) -> 0 | D6: =R6+R11 -> 0 | F6: =B6-D6 -> 0 | H6: =IFERROR(R9/B6,0) -> 0 | J6: =COUNTIF(BillsTbl_MonthlySpendingTemplate59[Paid?],TRUE())&" / "&COUNTA(BillsTbl_MonthlySpendingTemplate59[Bill Name]) -> 0 / 0 | M6: Needs Target | N6: =IF(N5="50/30/20",B6*0.5,IF(N5="70/20/10",B6*0.7,0)) -> 0 | O6: 70/20/10 | Q6: Needs Actual | R6: =O15+O17+O19+O21 -> 0 | T6: Needs | U6: =C37 -> Savings | V6: =R6 -> 0 | X6: Needs
M7: Wants Target | N7: =IF(N5="50/30/20",B6*0.3,IF(N5="70/20/10",B6*0.2,0)) -> 0 | Q7: Wants Actual | R7: =O14+O16+O18+O20 -> 0 | X7: Wants
C8: (Follow the numbers below for easy of use) | M8: Savings Target | N8: =IF(N5="50/30/20",B6*0.2,IF(N5="70/20/10",B6*0.1,0)) -> 0 | Q8: Savings Actual | R8: =SUM(SavingsTbl_MonthlySpendingTemplate60[Amount]) -> 0 | X8: Savings
Q9: Total Spent | R9: =R6+R7 -> 0
T11: Wants | U11: =C38 -> 401K | V11: =R11 -> 0
B12: 1. Income | E12: 2. Savings & Investments | I12: 4. Transactions Log | N12: Category Totals | T12: Savings | U12: =C39 -> Roth-IRA | V12: =R12 -> 0
B13: Source | C13: Amount | E13: Account | F13: Amount | I13: Date | J13: Category | K13: Amount | L13: Notes | N13: Category | O13: Total
N14: Subscriptions | O14: =SUMIFS(BillsTbl_MonthlySpendingTemplate59[Actual],BillsTbl_MonthlySpendingTemplate59[Category],"Subscriptions")+SUMIFS(K14:K72,J14:J72,"Subscriptions") -> 0 | Q14: want
N15: Gas | O15: =SUMIFS(BillsTbl_MonthlySpendingTemplate59[Actual],BillsTbl_MonthlySpendingTemplate59[Category],"Gas")+SUMIFS(K14:K72,J14:J72,"Gas") -> 0 | Q15: need
N16: Other | O16: =SUMIFS(BillsTbl_MonthlySpendingTemplate59[Actual],BillsTbl_MonthlySpendingTemplate59[Category],"Other")+SUMIFS(K14:K72,J14:J72,"Other") -> 0 | Q16: want
N17: Groceries | O17: =SUMIFS(BillsTbl_MonthlySpendingTemplate59[Actual],BillsTbl_MonthlySpendingTemplate59[Category],"Groceries")+SUMIFS(K14:K72,J14:J72,"Groceries") -> 0 | Q17: need
N18: Dining out | O18: =SUMIFS(BillsTbl_MonthlySpendingTemplate59[Actual],BillsTbl_MonthlySpendingTemplate59[Category],"Dining out")+SUMIFS(K14:K72,J14:J72,"Dining out") -> 0 | Q18: want
N19: Rent | O19: =SUMIFS(BillsTbl_MonthlySpendingTemplate59[Actual],BillsTbl_MonthlySpendingTemplate59[Category],"Rent")+SUMIFS(K14:K72,J14:J72,"Rent") -> 0 | Q19: need
N20: Shopping | O20: =SUMIFS(BillsTbl_MonthlySpendingTemplate59[Actual],BillsTbl_MonthlySpendingTemplate59[Category],"Shopping")+SUMIFS(K14:K72,J14:J72,"Shopping") -> 0 | Q20: want
B21: 3. Recurring Bills | N21: Credit Card | O21: =SUMIFS(BillsTbl_MonthlySpendingTemplate59[Actual],BillsTbl_MonthlySpendingTemplate59[Category],"Credit Card")+SUMIFS(K14:K72,J14:J72,"Credit Card") -> 0 | Q21: Need
B22: Bill Name | C22: Category | D22: Amount | E22: Paid? | F22: Actual
F23: =IF(E23=TRUE(),D23,0) -> 0
F24: =IF(E24=TRUE(),D24,0) -> 0
F25: =IF(E25=TRUE(),D25,0) -> 0
F26: =IF(E26=TRUE(),D26,0) -> 0
F27: =IF(E27=TRUE(),D27,0) -> 0
F28: =IF(E28=TRUE(),D28,0) -> 0
F29: =IF(E29=TRUE(),D29,0) -> 0
F30: =IF(E30=TRUE(),D30,0) -> 0
F31: =IF(E31=TRUE(),D31,0) -> 0
F32: =IF(E32=TRUE(),D32,0) -> 0
F33: =IF(E33=TRUE(),D33,0) -> 0
F34: =IF(E34=TRUE(),D34,0) -> 0
B36: Types of Saving/Investments
B37: 1 | C37: Savings
B38: 2 | C38: 401K
B39: 3 | C39: Roth-IRA
B40: 4 | C40: Brokerage

Sheet Yearly Overview
C2: Yearly Budget Dashboard
C6: Total Income (YTD) | F6: Total Spent (YTD) | I6: Avg Savings Rate | L6: Net Position (YTD)
C7: =SUM(E11:P11) -> 0 | F7: =SUM(E15:P15) -> 0 | I7: =IFERROR(AVERAGE(E17:P17),0) -> 0 | L7: =SUM(E16:P16) -> 0
C10: Monthly Summary | E10: Jan | F10: Feb | G10: Mar | H10: Apr | I10: May | J10: Jun | K10: Jul | L10: Aug | M10: Sept | N10: Oct | O10: Nov | P10: Dec
C11: Total Income | E11: =Jan!$B$6 -> 0 | F11: =Feb!$B$6 -> 0 | G11: =Mar!$B$6 -> 0 | H11: =Apr!$B$6 -> 0 | I11: =May!$B$6 -> 0 | J11: =Jun!$B$6 -> 0 | K11: =Jul!$B$6 -> 0 | L11: =Aug!$B$6 -> 0 | M11: =Sept!$B$6 -> 0 | N11: =Oct!$B$6 -> 0 | O11: =Nov!$B$6 -> 0 | P11: =Dec!$B$6 -> 0
C12: Needs Actual | E12: =Jan!$R$6 -> 0 | F12: =Feb!$R$6 -> 0 | G12: =Mar!$R$6 -> 0 | H12: =Apr!$R$6 -> 0 | I12: =May!$R$6 -> 0 | J12: =Jun!$R$6 -> 0 | K12: =Jul!$R$6 -> 0 | L12: =Aug!$R$6 -> 0 | M12: =Sept!$R$6 -> 0 | N12: =Oct!$R$6 -> 0 | O12: =Nov!$R$6 -> 0 | P12: =Dec!$R$6 -> 0
C13: Wants Actual | E13: =Jan!$R$7 -> 0 | F13: =Feb!$R$7 -> 0 | G13: =Mar!$R$7 -> 0 | H13: =Apr!$R$7 -> 0 | I13: =May!$R$7 -> 0 | J13: =Jun!$R$7 -> 0 | K13: =Jul!$R$7 -> 0 | L13: =Aug!$R$7 -> 0 | M13: =Sept!$R$7 -> 0 | N13: =Oct!$R$7 -> 0 | O13: =Nov!$R$7 -> 0 | P13: =Dec!$R$7 -> 0
C14: Savings Actual | E14: =Jan!$R$8 -> 0 | F14: =Feb!$R$8 -> 0 | G14: =Mar!$R$8 -> 0 | H14: =Apr!$R$8 -> 0 | I14: =May!$R$8 -> 0 | J14: =Jun!$R$8 -> 0 | K14: =Jul!$R$8 -> 0 | L14: =Aug!$R$8 -> 0 | M14: =Sept!$R$8 -> 0 | N14: =Oct!$R$8 -> 0 | O14: =Nov!$R$8 -> 0 | P14: =Dec!$R$8 -> 0
C15: Total Expenses | E15: =Jan!$R$9 -> 0 | F15: =Feb!$R$9 -> 0 | G15: =Mar!$R$9 -> 0 | H15: =Apr!$R$9 -> 0 | I15: =May!$R$9 -> 0 | J15: =Jun!$R$9 -> 0 | K15: =Jul!$R$9 -> 0 | L15: =Aug!$R$9 -> 0 | M15: =Sept!$R$9 -> 0 | N15: =Oct!$R$9 -> 0 | O15: =Nov!$R$9 -> 0 | P15: =Dec!$R$9 -> 0
C16: Cash Variance | E16: =Jan!$F$6 -> 0 | F16: =Feb!$F$6 -> 0 | G16: =Mar!$F$6 -> 0 | H16: =Apr!$F$6 -> 0 | I16: =May!$F$6 -> 0 | J16: =Jun!$F$6 -> 0 | K16: =Jul!$F$6 -> 0 | L16: =Aug!$F$6 -> 0 | M16: =Sept!$F$6 -> 0 | N16: =Oct!$F$6 -> 0 | O16: =Nov!$F$6 -> 0 | P16: =Dec!$F$6 -> 0
C17: Savings Rate % | E17: =Jan!$H$6 -> 0 | F17: =Feb!$H$6 -> 0 | G17: =Mar!$H$6 -> 0 | H17: =Apr!$H$6 -> 0 | I17: =May!$H$6 -> 0 | J17: =Jun!$H$6 -> 0 | K17: =Jul!$H$6 -> 0 | L17: =Aug!$H$6 -> 0 | M17: =Sept!$H$6 -> 0 | N17: =Oct!$H$6 -> 0 | O17: =Nov!$H$6 -> 0 | P17: =Dec!$H$6 -> 0
E19: (Keep Cells Absolute)
C20: Spending by Category
C21: Category | E21: Jan | F21: Feb | G21: Mar | H21: Apr | I21: May | J21: Jun | K21: Jul | L21: Aug | M21: Sept | N21: Oct | O21: Nov | P21: Dec | Q21: Avg/Active Mo. | R21: YTD Total
C22: Subscriptions | E22: =Jan!$O$14 -> 0 | F22: =Feb!$O$14 -> 0 | G22: =Mar!$O$14 -> 0 | H22: =Apr!$O$14 -> 0 | I22: =May!$O$14 -> 0 | J22: =Jun!$O$14 -> 0 | K22: =Jul!$O$14 -> 0 | L22: =Aug!$O$14 -> 0 | M22: =Sept!$O$14 -> 0 | N22: =Oct!$O$14 -> 0 | O22: =Nov!$O$14 -> 0 | P22: =Dec!$O$14 -> 0 | Q22: =IFERROR(AVERAGEIF(E22:P22,"<>0"),0) -> 0 | R22: =SUM(E22:P22) -> 0
C23: Gas | E23: =Jan!$O$15 -> 0 | F23: =Feb!$O$15 -> 0 | G23: =Mar!$O$15 -> 0 | H23: =Apr!$O$15 -> 0 | I23: =May!$O$15 -> 0 | J23: =Jun!$O$15 -> 0 | K23: =Jul!$O$15 -> 0 | L23: =Aug!$O$15 -> 0 | M23: =Sept!$O$15 -> 0 | N23: =Oct!$O$15 -> 0 | O23: =Nov!$O$15 -> 0 | P23: =Dec!$O$15 -> 0 | Q23: =IFERROR(AVERAGEIF(E23:P23,"<>0"),0) -> 0 | R23: =SUM(E23:P23) -> 0
C24: Other | E24: =Jan!$O$16 -> 0 | F24: =Feb!$O$16 -> 0 | G24: =Mar!$O$16 -> 0 | H24: =Apr!$O$16 -> 0 | I24: =May!$O$16 -> 0 | J24: =Jun!$O$16 -> 0 | K24: =Jul!$O$16 -> 0 | L24: =Aug!$O$16 -> 0 | M24: =Sept!$O$16 -> 0 | N24: =Oct!$O$16 -> 0 | O24: =Nov!$O$16 -> 0 | P24: =Dec!$O$16 -> 0 | Q24: =IFERROR(AVERAGEIF(E24:P24,"<>0"),0) -> 0 | R24: =SUM(E24:P24) -> 0
C25: Groceries | E25: =Jan!$O$17 -> 0 | F25: =Feb!$O$17 -> 0 | G25: =Mar!$O$17 -> 0 | H25: =Apr!$O$17 -> 0 | I25: =May!$O$17 -> 0 | J25: =Jun!$O$17 -> 0 | K25: =Jul!$O$17 -> 0 | L25: =Aug!$O$17 -> 0 | M25: =Sept!$O$17 -> 0 | N25: =Oct!$O$17 -> 0 | O25: =Nov!$O$17 -> 0 | P25: =Dec!$O$17 -> 0 | Q25: =IFERROR(AVERAGEIF(E25:P25,"<>0"),0) -> 0 | R25: =SUM(E25:P25) -> 0
C26: Dining out | E26: =Jan!$O$18 -> 0 | F26: =Feb!$O$18 -> 0 | G26: =Mar!$O$18 -> 0 | H26: =Apr!$O$18 -> 0 | I26: =May!$O$18 -> 0 | J26: =Jun!$O$18 -> 0 | K26: =Jul!$O$18 -> 0 | L26: =Aug!$O$18 -> 0 | M26: =Sept!$O$18 -> 0 | N26: =Oct!$O$18 -> 0 | O26: =Nov!$O$18 -> 0 | P26: =Dec!$O$18 -> 0 | Q26: =IFERROR(AVERAGEIF(E26:P26,"<>0"),0) -> 0 | R26: =SUM(E26:P26) -> 0
C27: Rent | E27: =Jan!$O$19 -> 0 | F27: =Feb!$O$19 -> 0 | G27: =Mar!$O$19 -> 0 | H27: =Apr!$O$19 -> 0 | I27: =May!$O$19 -> 0 | J27: =Jun!$O$19 -> 0 | K27: =Jul!$O$19 -> 0 | L27: =Aug!$O$19 -> 0 | M27: =Sept!$O$19 -> 0 | N27: =Oct!$O$19 -> 0 | O27: =Nov!$O$19 -> 0 | P27: =Dec!$O$19 -> 0 | Q27: =IFERROR(AVERAGEIF(E27:P27,"<>0"),0) -> 0 | R27: =SUM(E27:P27) -> 0
C28: Shopping | E28: =Jan!$O$20 -> 0 | F28: =Feb!$O$20 -> 0 | G28: =Mar!$O$20 -> 0 | H28: =Apr!$O$20 -> 0 | I28: =May!$O$20 -> 0 | J28: =Jun!$O$20 -> 0 | K28: =Jul!$O$20 -> 0 | L28: =Aug!$O$20 -> 0 | M28: =Sept!$O$20 -> 0 | N28: =Oct!$O$20 -> 0 | O28: =Nov!$O$20 -> 0 | P28: =Dec!$O$20 -> 0 | Q28: =IFERROR(AVERAGEIF(E28:P28,"<>0"),0) -> 0 | R28: =SUM(E28:P28) -> 0
C29: Credit Card | E29: =Jan!$O$21 -> 0 | F29: =Feb!$O$21 -> 0 | G29: =Mar!$O$21 -> 0 | H29: =Apr!$O$21 -> 0 | I29: =May!$O$21 -> 0 | J29: =Jun!$O$21 -> 0 | K29: =Jul!$O$21 -> 0 | L29: =Aug!$O$21 -> 0 | M29: =Sept!$O$21 -> 0 | N29: =Oct!$O$21 -> 0 | O29: =Nov!$O$21 -> 0 | P29: =Dec!$O$21 -> 0 | Q29: =IFERROR(AVERAGEIF(E29:P29,"<>0"),0) -> 0 | R29: =SUM(E29:P29) -> 0

Sheet Jan
B1: MONTHLY BUDGET TEMPLATE
B5: Total Income | D5: Total Spent | F5: Leftover | H5: Savings Rate | J5: Bills Paid | M5: Budget Split | N5: 50/30/20 | O5: 50/30/20 | Q5: Spending Breakdown | U5: Budgeted | V5: Actual
B6: =SUM(IncomeTbl_MonthlySpendingTemplate575[Amount]) -> 0 | D6: =R6+R11 -> 0 | F6: =B6-D6 -> 0 | H6: =IFERROR(R9/B6,0) -> 0 | J6: =COUNTIF(BillsTbl_MonthlySpendingTemplate596[Paid?],TRUE())&" / "&COUNTA(BillsTbl_MonthlySpendingTemplate596[Bill Name]) -> 0 / 0 | M6: Needs Target | N6: =IF(N5="50/30/20",B6*0.5,IF(N5="70/20/10",B6*0.7,0)) -> 0 | O6: 70/20/10 | Q6: Needs Actual | R6: =O15+O17+O19+O21 -> 0 | T6: Needs | U6: =C37 -> Savings | V6: =R6 -> 0 | X6: Needs
M7: Wants Target | N7: =IF(N5="50/30/20",B6*0.3,IF(N5="70/20/10",B6*0.2,0)) -> 0 | Q7: Wants Actual | R7: =O14+O16+O18+O20 -> 0 | X7: Wants
C8: (Follow the numbers below for easy of use) | M8: Savings Target | N8: =IF(N5="50/30/20",B6*0.2,IF(N5="70/20/10",B6*0.1,0)) -> 0 | Q8: Savings Actual | R8: =SUM(SavingsTbl_MonthlySpendingTemplate607[Amount]) -> 0 | X8: Savings
Q9: Total Spent | R9: =R6+R7 -> 0
T11: Wants | U11: =C38 -> 401K | V11: =R11 -> 0
B12: 1. Income | E12: 2. Savings & Investments | I12: 4. Transactions Log | N12: Category Totals | T12: Savings | U12: =C39 -> Roth-IRA | V12: =R12 -> 0
B13: Source | C13: Amount | E13: Account | F13: Amount | I13: Date | J13: Category | K13: Amount | L13: Notes | N13: Category | O13: Total
N14: Subscriptions | O14: =SUMIFS(BillsTbl_MonthlySpendingTemplate596[Actual],BillsTbl_MonthlySpendingTemplate596[Category],"Subscriptions")+SUMIFS(K14:K72,J14:J72,"Subscriptions") -> 0 | Q14: want
N15: Gas | O15: =SUMIFS(BillsTbl_MonthlySpendingTemplate596[Actual],BillsTbl_MonthlySpendingTemplate596[Category],"Gas")+SUMIFS(K14:K72,J14:J72,"Gas") -> 0 | Q15: need
N16: Other | O16: =SUMIFS(BillsTbl_MonthlySpendingTemplate596[Actual],BillsTbl_MonthlySpendingTemplate596[Category],"Other")+SUMIFS(K14:K72,J14:J72,"Other") -> 0 | Q16: want
N17: Groceries | O17: =SUMIFS(BillsTbl_MonthlySpendingTemplate596[Actual],BillsTbl_MonthlySpendingTemplate596[Category],"Groceries")+SUMIFS(K14:K72,J14:J72,"Groceries") -> 0 | Q17: need
N18: Dining out | O18: =SUMIFS(BillsTbl_MonthlySpendingTemplate596[Actual],BillsTbl_MonthlySpendingTemplate596[Category],"Dining out")+SUMIFS(K14:K72,J14:J72,"Dining out") -> 0 | Q18: want
N19: Rent | O19: =SUMIFS(BillsTbl_MonthlySpendingTemplate596[Actual],BillsTbl_MonthlySpendingTemplate596[Category],"Rent")+SUMIFS(K14:K72,J14:J72,"Rent") -> 0 | Q19: need
N20: Shopping | O20: =SUMIFS(BillsTbl_MonthlySpendingTemplate596[Actual],BillsTbl_MonthlySpendingTemplate596[Category],"Shopping")+SUMIFS(K14:K72,J14:J72,"Shopping") -> 0 | Q20: want
B21: 3. Recurring Bills | N21: Credit Card | O21: =SUMIFS(BillsTbl_MonthlySpendingTemplate596[Actual],BillsTbl_MonthlySpendingTemplate596[Category],"Credit Card")+SUMIFS(K14:K72,J14:J72,"Credit Card") -> 0 | Q21: Need
B22: Bill Name | C22: Category | D22: Amount | E22: Paid? | F22: Actual
F23: =IF(E23=TRUE(),D23,0) -> 0
F24: =IF(E24=TRUE(),D24,0) -> 0
F25: =IF(E25=TRUE(),D25,0) -> 0
F26: =IF(E26=TRUE(),D26,0) -> 0
F27: =IF(E27=TRUE(),D27,0) -> 0
F28: =IF(E28=TRUE(),D28,0) -> 0
F29: =IF(E29=TRUE(),D29,0) -> 0
F30: =IF(E30=TRUE(),D30,0) -> 0
F31: =IF(E31=TRUE(),D31,0) -> 0
F32: =IF(E32=TRUE(),D32,0) -> 0
F33: =IF(E33=TRUE(),D33,0) -> 0
F34: =IF(E34=TRUE(),D34,0) -> 0
B36: Types of Saving/Investments
B37: 1 | C37: Savings
B38: 2 | C38: 401K
B39: 3 | C39: Roth-IRA
B40: 4 | C40: Brokerage

Sheet Feb
B1: MONTHLY BUDGET TEMPLATE
B5: Total Income | D5: Total Spent | F5: Leftover | H5: Savings Rate | J5: Bills Paid | M5: Budget Split | N5: 50/30/20 | O5: 50/30/20 | Q5: Spending Breakdown | U5: Budgeted | V5: Actual
B6: =SUM(IncomeTbl_MonthlySpendingTemplate5758[Amount]) -> 0 | D6: =R6+R11 -> 0 | F6: =B6-D6 -> 0 | H6: =IFERROR(R9/B6,0) -> 0 | J6: =COUNTIF(BillsTbl_MonthlySpendingTemplate5969[Paid?],TRUE())&" / "&COUNTA(BillsTbl_MonthlySpendingTemplate5969[Bill Name]) -> 0 / 0 | M6: Needs Target | N6: =IF(N5="50/30/20",B6*0.5,IF(N5="70/20/10",B6*0.7,0)) -> 0 | O6: 70/20/10 | Q6: Needs Actual | R6: =O15+O17+O19+O21 -> 0 | T6: Needs | U6: =C37 -> Savings | V6: =R6 -> 0 | X6: Needs
M7: Wants Target | N7: =IF(N5="50/30/20",B6*0.3,IF(N5="70/20/10",B6*0.2,0)) -> 0 | Q7: Wants Actual | R7: =O14+O16+O18+O20 -> 0 | X7: Wants
C8: (Follow the numbers below for easy of use) | M8: Savings Target | N8: =IF(N5="50/30/20",B6*0.2,IF(N5="70/20/10",B6*0.1,0)) -> 0 | Q8: Savings Actual | R8: =SUM(SavingsTbl_MonthlySpendingTemplate60710[Amount]) -> 0 | X8: Savings
Q9: Total Spent | R9: =R6+R7 -> 0
T11: Wants | U11: =C38 -> 401K | V11: =R11 -> 0
B12: 1. Income | E12: 2. Savings & Investments | I12: 4. Transactions Log | N12: Category Totals | T12: Savings | U12: =C39 -> Roth-IRA | V12: =R12 -> 0
B13: Source | C13: Amount | E13: Account | F13: Amount | I13: Date | J13: Category | K13: Amount | L13: Notes | N13: Category | O13: Total
N14: Subscriptions | O14: =SUMIFS(BillsTbl_MonthlySpendingTemplate5969[Actual],BillsTbl_MonthlySpendingTemplate5969[Category],"Subscriptions")+SUMIFS(K14:K72,J14:J72,"Subscriptions") -> 0 | Q14: want
N15: Gas | O15: =SUMIFS(BillsTbl_MonthlySpendingTemplate5969[Actual],BillsTbl_MonthlySpendingTemplate5969[Category],"Gas")+SUMIFS(K14:K72,J14:J72,"Gas") -> 0 | Q15: need
N16: Other | O16: =SUMIFS(BillsTbl_MonthlySpendingTemplate5969[Actual],BillsTbl_MonthlySpendingTemplate5969[Category],"Other")+SUMIFS(K14:K72,J14:J72,"Other") -> 0 | Q16: want
N17: Groceries | O17: =SUMIFS(BillsTbl_MonthlySpendingTemplate5969[Actual],BillsTbl_MonthlySpendingTemplate5969[Category],"Groceries")+SUMIFS(K14:K72,J14:J72,"Groceries") -> 0 | Q17: need
N18: Dining out | O18: =SUMIFS(BillsTbl_MonthlySpendingTemplate5969[Actual],BillsTbl_MonthlySpendingTemplate5969[Category],"Dining out")+SUMIFS(K14:K72,J14:J72,"Dining out") -> 0 | Q18: want
N19: Rent | O19: =SUMIFS(BillsTbl_MonthlySpendingTemplate5969[Actual],BillsTbl_MonthlySpendingTemplate5969[Category],"Rent")+SUMIFS(K14:K72,J14:J72,"Rent") -> 0 | Q19: need
N20: Shopping | O20: =SUMIFS(BillsTbl_MonthlySpendingTemplate5969[Actual],BillsTbl_MonthlySpendingTemplate5969[Category],"Shopping")+SUMIFS(K14:K72,J14:J72,"Shopping") -> 0 | Q20: want
B21: 3. Recurring Bills | N21: Credit Card | O21: =SUMIFS(BillsTbl_MonthlySpendingTemplate5969[Actual],BillsTbl_MonthlySpendingTemplate5969[Category],"Credit Card")+SUMIFS(K14:K72,J14:J72,"Credit Card") -> 0 | Q21: Need
B22: Bill Name | C22: Category | D22: Amount | E22: Paid? | F22: Actual
F23: =IF(E23=TRUE(),D23,0) -> 0
F24: =IF(E24=TRUE(),D24,0) -> 0
F25: =IF(E25=TRUE(),D25,0) -> 0
F26: =IF(E26=TRUE(),D26,0) -> 0
F27: =IF(E27=TRUE(),D27,0) -> 0
F28: =IF(E28=TRUE(),D28,0) -> 0
F29: =IF(E29=TRUE(),D29,0) -> 0
F30: =IF(E30=TRUE(),D30,0) -> 0
F31: =IF(E31=TRUE(),D31,0) -> 0
F32: =IF(E32=TRUE(),D32,0) -> 0
F33: =IF(E33=TRUE(),D33,0) -> 0
F34: =IF(E34=TRUE(),D34,0) -> 0
B36: Types of Saving/Investments
B37: 1 | C37: Savings
B38: 2 | C38: 401K
B39: 3 | C39: Roth-IRA
B40: 4 | C40: Brokerage

Sheet Mar
B1: MONTHLY BUDGET TEMPLATE
B5: Total Income | D5: Total Spent | F5: Leftover | H5: Savings Rate | J5: Bills Paid | M5: Budget Split | N5: 50/30/20 | O5: 50/30/20 | Q5: Spending Breakdown | U5: Budgeted | V5: Actual
B6: =SUM(IncomeTbl_MonthlySpendingTemplate575811[Amount]) -> 0 | D6: =R6+R11 -> 0 | F6: =B6-D6 -> 0 | H6: =IFERROR(R9/B6,0) -> 0 | J6: =COUNTIF(BillsTbl_MonthlySpendingTemplate596912[Paid?],TRUE())&" / "&COUNTA(BillsTbl_MonthlySpendingTemplate596912[Bill Name]) -> 0 / 0 | M6: Needs Target | N6: =IF(N5="50/30/20",B6*0.5,IF(N5="70/20/10",B6*0.7,0)) -> 0 | O6: 70/20/10 | Q6: Needs Actual | R6: =O15+O17+O19+O21 -> 0 | T6: Needs | U6: =C37 -> Savings | V6: =R6 -> 0 | X6: Needs
M7: Wants Target | N7: =IF(N5="50/30/20",B6*0.3,IF(N5="70/20/10",B6*0.2,0)) -> 0 | Q7: Wants Actual | R7: =O14+O16+O18+O20 -> 0 | X7: Wants
C8: (Follow the numbers below for easy of use) | M8: Savings Target | N8: =IF(N5="50/30/20",B6*0.2,IF(N5="70/20/10",B6*0.1,0)) -> 0 | Q8: Savings Actual | R8: =SUM(SavingsTbl_MonthlySpendingTemplate6071013[Amount]) -> 0 | X8: Savings
Q9: Total Spent | R9: =R6+R7 -> 0
T11: Wants | U11: =C38 -> 401K | V11: =R11 -> 0
B12: 1. Income | E12: 2. Savings & Investments | I12: 4. Transactions Log | N12: Category Totals | T12: Savings | U12: =C39 -> Roth-IRA | V12: =R12 -> 0
B13: Source | C13: Amount | E13: Account | F13: Amount | I13: Date | J13: Category | K13: Amount | L13: Notes | N13: Category | O13: Total
N14: Subscriptions | O14: =SUMIFS(BillsTbl_MonthlySpendingTemplate596912[Actual],BillsTbl_MonthlySpendingTemplate596912[Category],"Subscriptions")+SUMIFS(K14:K72,J14:J72,"Subscriptions") -> 0 | Q14: want
N15: Gas | O15: =SUMIFS(BillsTbl_MonthlySpendingTemplate596912[Actual],BillsTbl_MonthlySpendingTemplate596912[Category],"Gas")+SUMIFS(K14:K72,J14:J72,"Gas") -> 0 | Q15: need
N16: Other | O16: =SUMIFS(BillsTbl_MonthlySpendingTemplate596912[Actual],BillsTbl_MonthlySpendingTemplate596912[Category],"Other")+SUMIFS(K14:K72,J14:J72,"Other") -> 0 | Q16: want
N17: Groceries | O17: =SUMIFS(BillsTbl_MonthlySpendingTemplate596912[Actual],BillsTbl_MonthlySpendingTemplate596912[Category],"Groceries")+SUMIFS(K14:K72,J14:J72,"Groceries") -> 0 | Q17: need
N18: Dining out | O18: =SUMIFS(BillsTbl_MonthlySpendingTemplate596912[Actual],BillsTbl_MonthlySpendingTemplate596912[Category],"Dining out")+SUMIFS(K14:K72,J14:J72,"Dining out") -> 0 | Q18: want
N19: Rent | O19: =SUMIFS(BillsTbl_MonthlySpendingTemplate596912[Actual],BillsTbl_MonthlySpendingTemplate596912[Category],"Rent")+SUMIFS(K14:K72,J14:J72,"Rent") -> 0 | Q19: need
N20: Shopping | O20: =SUMIFS(BillsTbl_MonthlySpendingTemplate596912[Actual],BillsTbl_MonthlySpendingTemplate596912[Category],"Shopping")+SUMIFS(K14:K72,J14:J72,"Shopping") -> 0 | Q20: want
B21: 3. Recurring Bills | N21: Credit Card | O21: =SUMIFS(BillsTbl_MonthlySpendingTemplate596912[Actual],BillsTbl_MonthlySpendingTemplate596912[Category],"Credit Card")+SUMIFS(K14:K72,J14:J72,"Credit Card") -> 0 | Q21: Need
B22: Bill Name | C22: Category | D22: Amount | E22: Paid? | F22: Actual
F23: =IF(E23=TRUE(),D23,0) -> 0
F24: =IF(E24=TRUE(),D24,0) -> 0
F25: =IF(E25=TRUE(),D25,0) -> 0
F26: =IF(E26=TRUE(),D26,0) -> 0
F27: =IF(E27=TRUE(),D27,0) -> 0
F28: =IF(E28=TRUE(),D28,0) -> 0
F29: =IF(E29=TRUE(),D29,0) -> 0
F30: =IF(E30=TRUE(),D30,0) -> 0
F31: =IF(E31=TRUE(),D31,0) -> 0
F32: =IF(E32=TRUE(),D32,0) -> 0
F33: =IF(E33=TRUE(),D33,0) -> 0
F34: =IF(E34=TRUE(),D34,0) -> 0
B36: Types of Saving/Investments
B37: 1 | C37: Savings
B38: 2 | C38: 401K
B39: 3 | C39: Roth-IRA
B40: 4 | C40: Brokerage

Sheet Apr
B1: MONTHLY BUDGET TEMPLATE
B5: Total Income | D5: Total Spent | F5: Leftover | H5: Savings Rate | J5: Bills Paid | M5: Budget Split | N5: 50/30/20 | O5: 50/30/20 | Q5: Spending Breakdown | U5: Budgeted | V5: Actual
B6: =SUM(IncomeTbl_MonthlySpendingTemplate57581114[Amount]) -> 0 | D6: =R6+R11 -> 0 | F6: =B6-D6 -> 0 | H6: =IFERROR(R9/B6,0) -> 0 | J6: =COUNTIF(BillsTbl_MonthlySpendingTemplate59691215[Paid?],TRUE())&" / "&COUNTA(BillsTbl_MonthlySpendingTemplate59691215[Bill Name]) -> 0 / 0 | M6: Needs Target | N6: =IF(N5="50/30/20",B6*0.5,IF(N5="70/20/10",B6*0.7,0)) -> 0 | O6: 70/20/10 | Q6: Needs Actual | R6: =O15+O17+O19+O21 -> 0 | T6: Needs | U6: =C37 -> Savings | V6: =R6 -> 0 | X6: Needs
M7: Wants Target | N7: =IF(N5="50/30/20",B6*0.3,IF(N5="70/20/10",B6*0.2,0)) -> 0 | Q7: Wants Actual | R7: =O14+O16+O18+O20 -> 0 | X7: Wants
C8: (Follow the numbers below for easy of use) | M8: Savings Target | N8: =IF(N5="50/30/20",B6*0.2,IF(N5="70/20/10",B6*0.1,0)) -> 0 | Q8: Savings Actual | R8: =SUM(SavingsTbl_MonthlySpendingTemplate607101316[Amount]) -> 0 | X8: Savings
Q9: Total Spent | R9: =R6+R7 -> 0
T11: Wants | U11: =C38 -> 401K | V11: =R11 -> 0
B12: 1. Income | E12: 2. Savings & Investments | I12: 4. Transactions Log | N12: Category Totals | T12: Savings | U12: =C39 -> Roth-IRA | V12: =R12 -> 0
B13: Source | C13: Amount | E13: Account | F13: Amount | I13: Date | J13: Category | K13: Amount | L13: Notes | N13: Category | O13: Total
N14: Subscriptions | O14: =SUMIFS(BillsTbl_MonthlySpendingTemplate59691215[Actual],BillsTbl_MonthlySpendingTemplate59691215[Category],"Subscriptions")+SUMIFS(K14:K72,J14:J72,"Subscriptions") -> 0 | Q14: want
N15: Gas | O15: =SUMIFS(BillsTbl_MonthlySpendingTemplate59691215[Actual],BillsTbl_MonthlySpendingTemplate59691215[Category],"Gas")+SUMIFS(K14:K72,J14:J72,"Gas") -> 0 | Q15: need
N16: Other | O16: =SUMIFS(BillsTbl_MonthlySpendingTemplate59691215[Actual],BillsTbl_MonthlySpendingTemplate59691215[Category],"Other")+SUMIFS(K14:K72,J14:J72,"Other") -> 0 | Q16: want
N17: Groceries | O17: =SUMIFS(BillsTbl_MonthlySpendingTemplate59691215[Actual],BillsTbl_MonthlySpendingTemplate59691215[Category],"Groceries")+SUMIFS(K14:K72,J14:J72,"Groceries") -> 0 | Q17: need
N18: Dining out | O18: =SUMIFS(BillsTbl_MonthlySpendingTemplate59691215[Actual],BillsTbl_MonthlySpendingTemplate59691215[Category],"Dining out")+SUMIFS(K14:K72,J14:J72,"Dining out") -> 0 | Q18: want
N19: Rent | O19: =SUMIFS(BillsTbl_MonthlySpendingTemplate59691215[Actual],BillsTbl_MonthlySpendingTemplate59691215[Category],"Rent")+SUMIFS(K14:K72,J14:J72,"Rent") -> 0 | Q19: need
N20: Shopping | O20: =SUMIFS(BillsTbl_MonthlySpendingTemplate59691215[Actual],BillsTbl_MonthlySpendingTemplate59691215[Category],"Shopping")+SUMIFS(K14:K72,J14:J72,"Shopping") -> 0 | Q20: want
B21: 3. Recurring Bills | N21: Credit Card | O21: =SUMIFS(BillsTbl_MonthlySpendingTemplate59691215[Actual],BillsTbl_MonthlySpendingTemplate59691215[Category],"Credit Card")+SUMIFS(K14:K72,J14:J72,"Credit Card") -> 0 | Q21: Need
B22: Bill Name | C22: Category | D22: Amount | E22: Paid? | F22: Actual
F23: =IF(E23=TRUE(),D23,0) -> 0
F24: =IF(E24=TRUE(),D24,0) -> 0
F25: =IF(E25=TRUE(),D25,0) -> 0
F26: =IF(E26=TRUE(),D26,0) -> 0
F27: =IF(E27=TRUE(),D27,0) -> 0
F28: =IF(E28=TRUE(),D28,0) -> 0
F29: =IF(E29=TRUE(),D29,0) -> 0
F30: =IF(E30=TRUE(),D30,0) -> 0
F31: =IF(E31=TRUE(),D31,0) -> 0
F32: =IF(E32=TRUE(),D32,0) -> 0
F33: =IF(E33=TRUE(),D33,0) -> 0
F34: =IF(E34=TRUE(),D34,0) -> 0
B36: Types of Saving/Investments
B37: 1 | C37: Savings
B38: 2 | C38: 401K
B39: 3 | C39: Roth-IRA
B40: 4 | C40: Brokerage

Sheet May
B1: MONTHLY BUDGET TEMPLATE
B5: Total Income | D5: Total Spent | F5: Leftover | H5: Savings Rate | J5: Bills Paid | M5: Budget Split | N5: 50/30/20 | O5: 50/30/20 | Q5: Spending Breakdown | U5: Budgeted | V5: Actual
B6: =SUM(IncomeTbl_MonthlySpendingTemplate5758111417[Amount]) -> 0 | D6: =R6+R11 -> 0 | F6: =B6-D6 -> 0 | H6: =IFERROR(R9/B6,0) -> 0 | J6: =COUNTIF(BillsTbl_MonthlySpendingTemplate5969121518[Paid?],TRUE())&" / "&COUNTA(BillsTbl_MonthlySpendingTemplate5969121518[Bill Name]) -> 0 / 0 | M6: Needs Target | N6: =IF(N5="50/30/20",B6*0.5,IF(N5="70/20/10",B6*0.7,0)) -> 0 | O6: 70/20/10 | Q6: Needs Actual | R6: =O15+O17+O19+O21 -> 0 | T6: Needs | U6: =C37 -> Savings | V6: =R6 -> 0 | X6: Needs
M7: Wants Target | N7: =IF(N5="50/30/20",B6*0.3,IF(N5="70/20/10",B6*0.2,0)) -> 0 | Q7: Wants Actual | R7: =O14+O16+O18+O20 -> 0 | X7: Wants
C8: (Follow the numbers below for easy of use) | M8: Savings Target | N8: =IF(N5="50/30/20",B6*0.2,IF(N5="70/20/10",B6*0.1,0)) -> 0 | Q8: Savings Actual | R8: =SUM(SavingsTbl_MonthlySpendingTemplate60710131619[Amount]) -> 0 | X8: Savings
Q9: Total Spent | R9: =R6+R7 -> 0
T11: Wants | U11: =C38 -> 401K | V11: =R11 -> 0
B12: 1. Income | E12: 2. Savings & Investments | I12: 4. Transactions Log | N12: Category Totals | T12: Savings | U12: =C39 -> Roth-IRA | V12: =R12 -> 0
B13: Source | C13: Amount | E13: Account | F13: Amount | I13: Date | J13: Category | K13: Amount | L13: Notes | N13: Category | O13: Total
N14: Subscriptions | O14: =SUMIFS(BillsTbl_MonthlySpendingTemplate5969121518[Actual],BillsTbl_MonthlySpendingTemplate5969121518[Category],"Subscriptions")+SUMIFS(K14:K72,J14:J72,"Subscriptions") -> 0 | Q14: want
N15: Gas | O15: =SUMIFS(BillsTbl_MonthlySpendingTemplate5969121518[Actual],BillsTbl_MonthlySpendingTemplate5969121518[Category],"Gas")+SUMIFS(K14:K72,J14:J72,"Gas") -> 0 | Q15: need
N16: Other | O16: =SUMIFS(BillsTbl_MonthlySpendingTemplate5969121518[Actual],BillsTbl_MonthlySpendingTemplate5969121518[Category],"Other")+SUMIFS(K14:K72,J14:J72,"Other") -> 0 | Q16: want
N17: Groceries | O17: =SUMIFS(BillsTbl_MonthlySpendingTemplate5969121518[Actual],BillsTbl_MonthlySpendingTemplate5969121518[Category],"Groceries")+SUMIFS(K14:K72,J14:J72,"Groceries") -> 0 | Q17: need
N18: Dining out | O18: =SUMIFS(BillsTbl_MonthlySpendingTemplate5969121518[Actual],BillsTbl_MonthlySpendingTemplate5969121518[Category],"Dining out")+SUMIFS(K14:K72,J14:J72,"Dining out") -> 0 | Q18: want
N19: Rent | O19: =SUMIFS(BillsTbl_MonthlySpendingTemplate5969121518[Actual],BillsTbl_MonthlySpendingTemplate5969121518[Category],"Rent")+SUMIFS(K14:K72,J14:J72,"Rent") -> 0 | Q19: need
N20: Shopping | O20: =SUMIFS(BillsTbl_MonthlySpendingTemplate5969121518[Actual],BillsTbl_MonthlySpendingTemplate5969121518[Category],"Shopping")+SUMIFS(K14:K72,J14:J72,"Shopping") -> 0 | Q20: want
B21: 3. Recurring Bills | N21: Credit Card | O21: =SUMIFS(BillsTbl_MonthlySpendingTemplate5969121518[Actual],BillsTbl_MonthlySpendingTemplate5969121518[Category],"Credit Card")+SUMIFS(K14:K72,J14:J72,"Credit Card") -> 0 | Q21: Need
B22: Bill Name | C22: Category | D22: Amount | E22: Paid? | F22: Actual
F23: =IF(E23=TRUE(),D23,0) -> 0
F24: =IF(E24=TRUE(),D24,0) -> 0
F25: =IF(E25=TRUE(),D25,0) -> 0
F26: =IF(E26=TRUE(),D26,0) -> 0
F27: =IF(E27=TRUE(),D27,0) -> 0
F28: =IF(E28=TRUE(),D28,0) -> 0
F29: =IF(E29=TRUE(),D29,0) -> 0
F30: =IF(E30=TRUE(),D30,0) -> 0
F31: =IF(E31=TRUE(),D31,0) -> 0
F32: =IF(E32=TRUE(),D32,0) -> 0
F33: =IF(E33=TRUE(),D33,0) -> 0
F34: =IF(E34=TRUE(),D34,0) -> 0
B36: Types of Saving/Investments
B37: 1 | C37: Savings
B38: 2 | C38: 401K
B39: 3 | C39: Roth-IRA
B40: 4 | C40: Brokerage

Sheet Jun
B1: MONTHLY BUDGET TEMPLATE
B5: Total Income | D5: Total Spent | F5: Leftover | H5: Savings Rate | J5: Bills Paid | M5: Budget Split | N5: 50/30/20 | O5: 50/30/20 | Q5: Spending Breakdown | U5: Budgeted | V5: Actual
B6: =SUM(IncomeTbl_MonthlySpendingTemplate575811141720[Amount]) -> 0 | D6: =R6+R11 -> 0 | F6: =B6-D6 -> 0 | H6: =IFERROR(R9/B6,0) -> 0 | J6: =COUNTIF(BillsTbl_MonthlySpendingTemplate596912151821[Paid?],TRUE())&" / "&COUNTA(BillsTbl_MonthlySpendingTemplate596912151821[Bill Name]) -> 0 / 0 | M6: Needs Target | N6: =IF(N5="50/30/20",B6*0.5,IF(N5="70/20/10",B6*0.7,0)) -> 0 | O6: 70/20/10 | Q6: Needs Actual | R6: =O15+O17+O19+O21 -> 0 | T6: Needs | U6: =C37 -> Savings | V6: =R6 -> 0 | X6: Needs
M7: Wants Target | N7: =IF(N5="50/30/20",B6*0.3,IF(N5="70/20/10",B6*0.2,0)) -> 0 | Q7: Wants Actual | R7: =O14+O16+O18+O20 -> 0 | X7: Wants
C8: (Follow the numbers below for easy of use) | M8: Savings Target | N8: =IF(N5="50/30/20",B6*0.2,IF(N5="70/20/10",B6*0.1,0)) -> 0 | Q8: Savings Actual | R8: =SUM(SavingsTbl_MonthlySpendingTemplate6071013161922[Amount]) -> 0 | X8: Savings
Q9: Total Spent | R9: =R6+R7 -> 0
T11: Wants | U11: =C38 -> 401K | V11: =R11 -> 0
B12: 1. Income | E12: 2. Savings & Investments | I12: 4. Transactions Log | N12: Category Totals | T12: Savings | U12: =C39 -> Roth-IRA | V12: =R12 -> 0
B13: Source | C13: Amount | E13: Account | F13: Amount | I13: Date | J13: Category | K13: Amount | L13: Notes | N13: Category | O13: Total
N14: Subscriptions | O14: =SUMIFS(BillsTbl_MonthlySpendingTemplate596912151821[Actual],BillsTbl_MonthlySpendingTemplate596912151821[Category],"Subscriptions")+SUMIFS(K14:K72,J14:J72,"Subscriptions") -> 0 | Q14: want
N15: Gas | O15: =SUMIFS(BillsTbl_MonthlySpendingTemplate596912151821[Actual],BillsTbl_MonthlySpendingTemplate596912151821[Category],"Gas")+SUMIFS(K14:K72,J14:J72,"Gas") -> 0 | Q15: need
N16: Other | O16: =SUMIFS(BillsTbl_MonthlySpendingTemplate596912151821[Actual],BillsTbl_MonthlySpendingTemplate596912151821[Category],"Other")+SUMIFS(K14:K72,J14:J72,"Other") -> 0 | Q16: want
N17: Groceries | O17: =SUMIFS(BillsTbl_MonthlySpendingTemplate596912151821[Actual],BillsTbl_MonthlySpendingTemplate596912151821[Category],"Groceries")+SUMIFS(K14:K72,J14:J72,"Groceries") -> 0 | Q17: need
N18: Dining out | O18: =SUMIFS(BillsTbl_MonthlySpendingTemplate596912151821[Actual],BillsTbl_MonthlySpendingTemplate596912151821[Category],"Dining out")+SUMIFS(K14:K72,J14:J72,"Dining out") -> 0 | Q18: want
N19: Rent | O19: =SUMIFS(BillsTbl_MonthlySpendingTemplate596912151821[Actual],BillsTbl_MonthlySpendingTemplate596912151821[Category],"Rent")+SUMIFS(K14:K72,J14:J72,"Rent") -> 0 | Q19: need
N20: Shopping | O20: =SUMIFS(BillsTbl_MonthlySpendingTemplate596912151821[Actual],BillsTbl_MonthlySpendingTemplate596912151821[Category],"Shopping")+SUMIFS(K14:K72,J14:J72,"Shopping") -> 0 | Q20: want
B21: 3. Recurring Bills | N21: Credit Card | O21: =SUMIFS(BillsTbl_MonthlySpendingTemplate596912151821[Actual],BillsTbl_MonthlySpendingTemplate596912151821[Category],"Credit Card")+SUMIFS(K14:K72,J14:J72,"Credit Card") -> 0 | Q21: Need
B22: Bill Name | C22: Category | D22: Amount | E22: Paid? | F22: Actual
F23: =IF(E23=TRUE(),D23,0) -> 0
F24: =IF(E24=TRUE(),D24,0) -> 0
F25: =IF(E25=TRUE(),D25,0) -> 0
F26: =IF(E26=TRUE(),D26,0) -> 0
F27: =IF(E27=TRUE(),D27,0) -> 0
F28: =IF(E28=TRUE(),D28,0) -> 0
F29: =IF(E29=TRUE(),D29,0) -> 0
F30: =IF(E30=TRUE(),D30,0) -> 0
F31: =IF(E31=TRUE(),D31,0) -> 0
F32: =IF(E32=TRUE(),D32,0) -> 0
F33: =IF(E33=TRUE(),D33,0) -> 0
F34: =IF(E34=TRUE(),D34,0) -> 0
B36: Types of Saving/Investments
B37: 1 | C37: Savings
B38: 2 | C38: 401K
B39: 3 | C39: Roth-IRA
B40: 4 | C40: Brokerage

Sheet Jul
B1: MONTHLY BUDGET TEMPLATE
B5: Total Income | D5: Total Spent | F5: Leftover | H5: Savings Rate | J5: Bills Paid | M5: Budget Split | N5: 50/30/20 | O5: 50/30/20 | Q5: Spending Breakdown | U5: Budgeted | V5: Actual
B6: =SUM(IncomeTbl_MonthlySpendingTemplate57581114172023[Amount]) -> 0 | D6: =R6+R11 -> 0 | F6: =B6-D6 -> 0 | H6: =IFERROR(R9/B6,0) -> 0 | J6: =COUNTIF(BillsTbl_MonthlySpendingTemplate59691215182124[Paid?],TRUE())&" / "&COUNTA(BillsTbl_MonthlySpendingTemplate59691215182124[Bill Name]) -> 0 / 0 | M6: Needs Target | N6: =IF(N5="50/30/20",B6*0.5,IF(N5="70/20/10",B6*0.7,0)) -> 0 | O6: 70/20/10 | Q6: Needs Actual | R6: =O15+O17+O19+O21 -> 0 | T6: Needs | U6: =C37 -> Savings | V6: =R6 -> 0 | X6: Needs
M7: Wants Target | N7: =IF(N5="50/30/20",B6*0.3,IF(N5="70/20/10",B6*0.2,0)) -> 0 | Q7: Wants Actual | R7: =O14+O16+O18+O20 -> 0 | X7: Wants
C8: (Follow the numbers below for easy of use) | M8: Savings Target | N8: =IF(N5="50/30/20",B6*0.2,IF(N5="70/20/10",B6*0.1,0)) -> 0 | Q8: Savings Actual | R8: =SUM(SavingsTbl_MonthlySpendingTemplate607101316192225[Amount]) -> 0 | X8: Savings
Q9: Total Spent | R9: =R6+R7 -> 0
T11: Wants | U11: =C38 -> 401K | V11: =R11 -> 0
B12: 1. Income | E12: 2. Savings & Investments | I12: 4. Transactions Log | N12: Category Totals | T12: Savings | U12: =C39 -> Roth-IRA | V12: =R12 -> 0
B13: Source | C13: Amount | E13: Account | F13: Amount | I13: Date | J13: Category | K13: Amount | L13: Notes | N13: Category | O13: Total
N14: Subscriptions | O14: =SUMIFS(BillsTbl_MonthlySpendingTemplate59691215182124[Actual],BillsTbl_MonthlySpendingTemplate59691215182124[Category],"Subscriptions")+SUMIFS(K14:K72,J14:J72,"Subscriptions") -> 0 | Q14: want
N15: Gas | O15: =SUMIFS(BillsTbl_MonthlySpendingTemplate59691215182124[Actual],BillsTbl_MonthlySpendingTemplate59691215182124[Category],"Gas")+SUMIFS(K14:K72,J14:J72,"Gas") -> 0 | Q15: need
N16: Other | O16: =SUMIFS(BillsTbl_MonthlySpendingTemplate59691215182124[Actual],BillsTbl_MonthlySpendingTemplate59691215182124[Category],"Other")+SUMIFS(K14:K72,J14:J72,"Other") -> 0 | Q16: want
N17: Groceries | O17: =SUMIFS(BillsTbl_MonthlySpendingTemplate59691215182124[Actual],BillsTbl_MonthlySpendingTemplate59691215182124[Category],"Groceries")+SUMIFS(K14:K72,J14:J72,"Groceries") -> 0 | Q17: need
N18: Dining out | O18: =SUMIFS(BillsTbl_MonthlySpendingTemplate59691215182124[Actual],BillsTbl_MonthlySpendingTemplate59691215182124[Category],"Dining out")+SUMIFS(K14:K72,J14:J72,"Dining out") -> 0 | Q18: want
N19: Rent | O19: =SUMIFS(BillsTbl_MonthlySpendingTemplate59691215182124[Actual],BillsTbl_MonthlySpendingTemplate59691215182124[Category],"Rent")+SUMIFS(K14:K72,J14:J72,"Rent") -> 0 | Q19: need
N20: Shopping | O20: =SUMIFS(BillsTbl_MonthlySpendingTemplate59691215182124[Actual],BillsTbl_MonthlySpendingTemplate59691215182124[Category],"Shopping")+SUMIFS(K14:K72,J14:J72,"Shopping") -> 0 | Q20: want
B21: 3. Recurring Bills | N21: Credit Card | O21: =SUMIFS(BillsTbl_MonthlySpendingTemplate59691215182124[Actual],BillsTbl_MonthlySpendingTemplate59691215182124[Category],"Credit Card")+SUMIFS(K14:K72,J14:J72,"Credit Card") -> 0 | Q21: Need
B22: Bill Name | C22: Category | D22: Amount | E22: Paid? | F22: Actual
F23: =IF(E23=TRUE(),D23,0) -> 0
F24: =IF(E24=TRUE(),D24,0) -> 0
F25: =IF(E25=TRUE(),D25,0) -> 0
F26: =IF(E26=TRUE(),D26,0) -> 0
F27: =IF(E27=TRUE(),D27,0) -> 0
F28: =IF(E28=TRUE(),D28,0) -> 0
F29: =IF(E29=TRUE(),D29,0) -> 0
F30: =IF(E30=TRUE(),D30,0) -> 0
F31: =IF(E31=TRUE(),D31,0) -> 0
F32: =IF(E32=TRUE(),D32,0) -> 0
F33: =IF(E33=TRUE(),D33,0) -> 0
F34: =IF(E34=TRUE(),D34,0) -> 0
B36: Types of Saving/Investments
B37: 1 | C37: Savings
B38: 2 | C38: 401K
B39: 3 | C39: Roth-IRA
B40: 4 | C40: Brokerage

Sheet Aug
B1: MONTHLY BUDGET TEMPLATE
B5: Total Income | D5: Total Spent | F5: Leftover | H5: Savings Rate | J5: Bills Paid | M5: Budget Split | N5: 50/30/20 | O5: 50/30/20 | Q5: Spending Breakdown | U5: Budgeted | V5: Actual
B6: =SUM(IncomeTbl_MonthlySpendingTemplate5758111417202326[Amount]) -> 0 | D6: =R6+R11 -> 0 | F6: =B6-D6 -> 0 | H6: =IFERROR(R9/B6,0) -> 0 | J6: =COUNTIF(BillsTbl_MonthlySpendingTemplate5969121518212427[Paid?],TRUE())&" / "&COUNTA(BillsTbl_MonthlySpendingTemplate5969121518212427[Bill Name]) -> 0 / 0 | M6: Needs Target | N6: =IF(N5="50/30/20",B6*0.5,IF(N5="70/20/10",B6*0.7,0)) -> 0 | O6: 70/20/10 | Q6: Needs Actual | R6: =O15+O17+O19+O21 -> 0 | T6: Needs | U6: =C37 -> Savings | V6: =R6 -> 0 | X6: Needs
M7: Wants Target | N7: =IF(N5="50/30/20",B6*0.3,IF(N5="70/20/10",B6*0.2,0)) -> 0 | Q7: Wants Actual | R7: =O14+O16+O18+O20 -> 0 | X7: Wants
C8: (Follow the numbers below for easy of use) | M8: Savings Target | N8: =IF(N5="50/30/20",B6*0.2,IF(N5="70/20/10",B6*0.1,0)) -> 0 | Q8: Savings Actual | R8: =SUM(SavingsTbl_MonthlySpendingTemplate60710131619222528[Amount]) -> 0 | X8: Savings
Q9: Total Spent | R9: =R6+R7 -> 0
T11: Wants | U11: =C38 -> 401K | V11: =R11 -> 0
B12: 1. Income | E12: 2. Savings & Investments | I12: 4. Transactions Log | N12: Category Totals | T12: Savings | U12: =C39 -> Roth-IRA | V12: =R12 -> 0
B13: Source | C13: Amount | E13: Account | F13: Amount | I13: Date | J13: Category | K13: Amount | L13: Notes | N13: Category | O13: Total
N14: Subscriptions | O14: =SUMIFS(BillsTbl_MonthlySpendingTemplate5969121518212427[Actual],BillsTbl_MonthlySpendingTemplate5969121518212427[Category],"Subscriptions")+SUMIFS(K14:K72,J14:J72,"Subscriptions") -> 0 | Q14: want
N15: Gas | O15: =SUMIFS(BillsTbl_MonthlySpendingTemplate5969121518212427[Actual],BillsTbl_MonthlySpendingTemplate5969121518212427[Category],"Gas")+SUMIFS(K14:K72,J14:J72,"Gas") -> 0 | Q15: need
N16: Other | O16: =SUMIFS(BillsTbl_MonthlySpendingTemplate5969121518212427[Actual],BillsTbl_MonthlySpendingTemplate5969121518212427[Category],"Other")+SUMIFS(K14:K72,J14:J72,"Other") -> 0 | Q16: want
N17: Groceries | O17: =SUMIFS(BillsTbl_MonthlySpendingTemplate5969121518212427[Actual],BillsTbl_MonthlySpendingTemplate5969121518212427[Category],"Groceries")+SUMIFS(K14:K72,J14:J72,"Groceries") -> 0 | Q17: need
N18: Dining out | O18: =SUMIFS(BillsTbl_MonthlySpendingTemplate5969121518212427[Actual],BillsTbl_MonthlySpendingTemplate5969121518212427[Category],"Dining out")+SUMIFS(K14:K72,J14:J72,"Dining out") -> 0 | Q18: want
N19: Rent | O19: =SUMIFS(BillsTbl_MonthlySpendingTemplate5969121518212427[Actual],BillsTbl_MonthlySpendingTemplate5969121518212427[Category],"Rent")+SUMIFS(K14:K72,J14:J72,"Rent") -> 0 | Q19: need
N20: Shopping | O20: =SUMIFS(BillsTbl_MonthlySpendingTemplate5969121518212427[Actual],BillsTbl_MonthlySpendingTemplate5969121518212427[Category],"Shopping")+SUMIFS(K14:K72,J14:J72,"Shopping") -> 0 | Q20: want
B21: 3. Recurring Bills | N21: Credit Card | O21: =SUMIFS(BillsTbl_MonthlySpendingTemplate5969121518212427[Actual],BillsTbl_MonthlySpendingTemplate5969121518212427[Category],"Credit Card")+SUMIFS(K14:K72,J14:J72,"Credit Card") -> 0 | Q21: Need
B22: Bill Name | C22: Category | D22: Amount | E22: Paid? | F22: Actual
F23: =IF(E23=TRUE(),D23,0) -> 0
F24: =IF(E24=TRUE(),D24,0) -> 0
F25: =IF(E25=TRUE(),D25,0) -> 0
F26: =IF(E26=TRUE(),D26,0) -> 0
F27: =IF(E27=TRUE(),D27,0) -> 0
F28: =IF(E28=TRUE(),D28,0) -> 0
F29: =IF(E29=TRUE(),D29,0) -> 0
F30: =IF(E30=TRUE(),D30,0) -> 0
F31: =IF(E31=TRUE(),D31,0) -> 0
F32: =IF(E32=TRUE(),D32,0) -> 0
F33: =IF(E33=TRUE(),D33,0) -> 0
F34: =IF(E34=TRUE(),D34,0) -> 0
B36: Types of Saving/Investments
B37: 1 | C37: Savings
B38: 2 | C38: 401K
B39: 3 | C39: Roth-IRA
B40: 4 | C40: Brokerage

Sheet Sept
B1: MONTHLY BUDGET TEMPLATE
B5: Total Income | D5: Total Spent | F5: Leftover | H5: Savings Rate | J5: Bills Paid | M5: Budget Split | N5: 50/30/20 | O5: 50/30/20 | Q5: Spending Breakdown | U5: Budgeted | V5: Actual
B6: =SUM(IncomeTbl_MonthlySpendingTemplate575811141720232629[Amount]) -> 0 | D6: =R6+R11 -> 0 | F6: =B6-D6 -> 0 | H6: =IFERROR(R9/B6,0) -> 0 | J6: =COUNTIF(BillsTbl_MonthlySpendingTemplate596912151821242730[Paid?],TRUE())&" / "&COUNTA(BillsTbl_MonthlySpendingTemplate596912151821242730[Bill Name]) -> 0 / 0 | M6: Needs Target | N6: =IF(N5="50/30/20",B6*0.5,IF(N5="70/20/10",B6*0.7,0)) -> 0 | O6: 70/20/10 | Q6: Needs Actual | R6: =O15+O17+O19+O21 -> 0 | T6: Needs | U6: =C37 -> Savings | V6: =R6 -> 0 | X6: Needs
M7: Wants Target | N7: =IF(N5="50/30/20",B6*0.3,IF(N5="70/20/10",B6*0.2,0)) -> 0 | Q7: Wants Actual | R7: =O14+O16+O18+O20 -> 0 | X7: Wants
C8: (Follow the numbers below for easy of use) | M8: Savings Target | N8: =IF(N5="50/30/20",B6*0.2,IF(N5="70/20/10",B6*0.1,0)) -> 0 | Q8: Savings Actual | R8: =SUM(SavingsTbl_MonthlySpendingTemplate6071013161922252831[Amount]) -> 0 | X8: Savings
Q9: Total Spent | R9: =R6+R7 -> 0
T11: Wants | U11: =C38 -> 401K | V11: =R11 -> 0
B12: 1. Income | E12: 2. Savings & Investments | I12: 4. Transactions Log | N12: Category Totals | T12: Savings | U12: =C39 -> Roth-IRA | V12: =R12 -> 0
B13: Source | C13: Amount | E13: Account | F13: Amount | I13: Date | J13: Category | K13: Amount | L13: Notes | N13: Category | O13: Total
N14: Subscriptions | O14: =SUMIFS(BillsTbl_MonthlySpendingTemplate596912151821242730[Actual],BillsTbl_MonthlySpendingTemplate596912151821242730[Category],"Subscriptions")+SUMIFS(K14:K72,J14:J72,"Subscriptions") -> 0 | Q14: want
N15: Gas | O15: =SUMIFS(BillsTbl_MonthlySpendingTemplate596912151821242730[Actual],BillsTbl_MonthlySpendingTemplate596912151821242730[Category],"Gas")+SUMIFS(K14:K72,J14:J72,"Gas") -> 0 | Q15: need
N16: Other | O16: =SUMIFS(BillsTbl_MonthlySpendingTemplate596912151821242730[Actual],BillsTbl_MonthlySpendingTemplate596912151821242730[Category],"Other")+SUMIFS(K14:K72,J14:J72,"Other") -> 0 | Q16: want
N17: Groceries | O17: =SUMIFS(BillsTbl_MonthlySpendingTemplate596912151821242730[Actual],BillsTbl_MonthlySpendingTemplate596912151821242730[Category],"Groceries")+SUMIFS(K14:K72,J14:J72,"Groceries") -> 0 | Q17: need
N18: Dining out | O18: =SUMIFS(BillsTbl_MonthlySpendingTemplate596912151821242730[Actual],BillsTbl_MonthlySpendingTemplate596912151821242730[Category],"Dining out")+SUMIFS(K14:K72,J14:J72,"Dining out") -> 0 | Q18: want
N19: Rent | O19: =SUMIFS(BillsTbl_MonthlySpendingTemplate596912151821242730[Actual],BillsTbl_MonthlySpendingTemplate596912151821242730[Category],"Rent")+SUMIFS(K14:K72,J14:J72,"Rent") -> 0 | Q19: need
N20: Shopping | O20: =SUMIFS(BillsTbl_MonthlySpendingTemplate596912151821242730[Actual],BillsTbl_MonthlySpendingTemplate596912151821242730[Category],"Shopping")+SUMIFS(K14:K72,J14:J72,"Shopping") -> 0 | Q20: want
B21: 3. Recurring Bills | N21: Credit Card | O21: =SUMIFS(BillsTbl_MonthlySpendingTemplate596912151821242730[Actual],BillsTbl_MonthlySpendingTemplate596912151821242730[Category],"Credit Card")+SUMIFS(K14:K72,J14:J72,"Credit Card") -> 0 | Q21: Need
B22: Bill Name | C22: Category | D22: Amount | E22: Paid? | F22: Actual
F23: =IF(E23=TRUE(),D23,0) -> 0
F24: =IF(E24=TRUE(),D24,0) -> 0
F25: =IF(E25=TRUE(),D25,0) -> 0
F26: =IF(E26=TRUE(),D26,0) -> 0
F27: =IF(E27=TRUE(),D27,0) -> 0
F28: =IF(E28=TRUE(),D28,0) -> 0
F29: =IF(E29=TRUE(),D29,0) -> 0
F30: =IF(E30=TRUE(),D30,0) -> 0
F31: =IF(E31=TRUE(),D31,0) -> 0
F32: =IF(E32=TRUE(),D32,0) -> 0
F33: =IF(E33=TRUE(),D33,0) -> 0
F34: =IF(E34=TRUE(),D34,0) -> 0
B36: Types of Saving/Investments
B37: 1 | C37: Savings
B38: 2 | C38: 401K
B39: 3 | C39: Roth-IRA
B40: 4 | C40: Brokerage

Sheet Oct
B1: MONTHLY BUDGET TEMPLATE
B5: Total Income | D5: Total Spent | F5: Leftover | H5: Savings Rate | J5: Bills Paid | M5: Budget Split | N5: 50/30/20 | O5: 50/30/20 | Q5: Spending Breakdown | U5: Budgeted | V5: Actual
B6: =SUM(IncomeTbl_MonthlySpendingTemplate57581114172023262932[Amount]) -> 0 | D6: =R6+R11 -> 0 | F6: =B6-D6 -> 0 | H6: =IFERROR(R9/B6,0) -> 0 | J6: =COUNTIF(BillsTbl_MonthlySpendingTemplate59691215182124273033[Paid?],TRUE())&" / "&COUNTA(BillsTbl_MonthlySpendingTemplate59691215182124273033[Bill Name]) -> 0 / 0 | M6: Needs Target | N6: =IF(N5="50/30/20",B6*0.5,IF(N5="70/20/10",B6*0.7,0)) -> 0 | O6: 70/20/10 | Q6: Needs Actual | R6: =O15+O17+O19+O21 -> 0 | T6: Needs | U6: =C37 -> Savings | V6: =R6 -> 0 | X6: Needs
M7: Wants Target | N7: =IF(N5="50/30/20",B6*0.3,IF(N5="70/20/10",B6*0.2,0)) -> 0 | Q7: Wants Actual | R7: =O14+O16+O18+O20 -> 0 | X7: Wants
C8: (Follow the numbers below for easy of use) | M8: Savings Target | N8: =IF(N5="50/30/20",B6*0.2,IF(N5="70/20/10",B6*0.1,0)) -> 0 | Q8: Savings Actual | R8: =SUM(SavingsTbl_MonthlySpendingTemplate607101316192225283134[Amount]) -> 0 | X8: Savings
Q9: Total Spent | R9: =R6+R7 -> 0
T11: Wants | U11: =C38 -> 401K | V11: =R11 -> 0
B12: 1. Income | E12: 2. Savings & Investments | I12: 4. Transactions Log | N12: Category Totals | T12: Savings | U12: =C39 -> Roth-IRA | V12: =R12 -> 0
B13: Source | C13: Amount | E13: Account | F13: Amount | I13: Date | J13: Category | K13: Amount | L13: Notes | N13: Category | O13: Total
N14: Subscriptions | O14: =SUMIFS(BillsTbl_MonthlySpendingTemplate59691215182124273033[Actual],BillsTbl_MonthlySpendingTemplate59691215182124273033[Category],"Subscriptions")+SUMIFS(K14:K72,J14:J72,"Subscriptions") -> 0 | Q14: want
N15: Gas | O15: =SUMIFS(BillsTbl_MonthlySpendingTemplate59691215182124273033[Actual],BillsTbl_MonthlySpendingTemplate59691215182124273033[Category],"Gas")+SUMIFS(K14:K72,J14:J72,"Gas") -> 0 | Q15: need
N16: Other | O16: =SUMIFS(BillsTbl_MonthlySpendingTemplate59691215182124273033[Actual],BillsTbl_MonthlySpendingTemplate59691215182124273033[Category],"Other")+SUMIFS(K14:K72,J14:J72,"Other") -> 0 | Q16: want
N17: Groceries | O17: =SUMIFS(BillsTbl_MonthlySpendingTemplate59691215182124273033[Actual],BillsTbl_MonthlySpendingTemplate59691215182124273033[Category],"Groceries")+SUMIFS(K14:K72,J14:J72,"Groceries") -> 0 | Q17: need
N18: Dining out | O18: =SUMIFS(BillsTbl_MonthlySpendingTemplate59691215182124273033[Actual],BillsTbl_MonthlySpendingTemplate59691215182124273033[Category],"Dining out")+SUMIFS(K14:K72,J14:J72,"Dining out") -> 0 | Q18: want
N19: Rent | O19: =SUMIFS(BillsTbl_MonthlySpendingTemplate59691215182124273033[Actual],BillsTbl_MonthlySpendingTemplate59691215182124273033[Category],"Rent")+SUMIFS(K14:K72,J14:J72,"Rent") -> 0 | Q19: need
N20: Shopping | O20: =SUMIFS(BillsTbl_MonthlySpendingTemplate59691215182124273033[Actual],BillsTbl_MonthlySpendingTemplate59691215182124273033[Category],"Shopping")+SUMIFS(K14:K72,J14:J72,"Shopping") -> 0 | Q20: want
B21: 3. Recurring Bills | N21: Credit Card | O21: =SUMIFS(BillsTbl_MonthlySpendingTemplate59691215182124273033[Actual],BillsTbl_MonthlySpendingTemplate59691215182124273033[Category],"Credit Card")+SUMIFS(K14:K72,J14:J72,"Credit Card") -> 0 | Q21: Need
B22: Bill Name | C22: Category | D22: Amount | E22: Paid? | F22: Actual
F23: =IF(E23=TRUE(),D23,0) -> 0
F24: =IF(E24=TRUE(),D24,0) -> 0
F25: =IF(E25=TRUE(),D25,0) -> 0
F26: =IF(E26=TRUE(),D26,0) -> 0
F27: =IF(E27=TRUE(),D27,0) -> 0
F28: =IF(E28=TRUE(),D28,0) -> 0
F29: =IF(E29=TRUE(),D29,0) -> 0
F30: =IF(E30=TRUE(),D30,0) -> 0
F31: =IF(E31=TRUE(),D31,0) -> 0
F32: =IF(E32=TRUE(),D32,0) -> 0
F33: =IF(E33=TRUE(),D33,0) -> 0
F34: =IF(E34=TRUE(),D34,0) -> 0
B36: Types of Saving/Investments
B37: 1 | C37: Savings
B38: 2 | C38: 401K
B39: 3 | C39: Roth-IRA
B40: 4 | C40: Brokerage

Sheet Nov
B1: MONTHLY BUDGET TEMPLATE
B5: Total Income | D5: Total Spent | F5: Leftover | H5: Savings Rate | J5: Bills Paid | M5: Budget Split | N5: 50/30/20 | O5: 50/30/20 | Q5: Spending Breakdown | U5: Budgeted | V5: Actual
B6: =SUM(IncomeTbl_MonthlySpendingTemplate5758111417202326293235[Amount]) -> 0 | D6: =R6+R11 -> 0 | F6: =B6-D6 -> 0 | H6: =IFERROR(R9/B6,0) -> 0 | J6: =COUNTIF(BillsTbl_MonthlySpendingTemplate5969121518212427303336[Paid?],TRUE())&" / "&COUNTA(BillsTbl_MonthlySpendingTemplate5969121518212427303336[Bill Name]) -> 0 / 0 | M6: Needs Target | N6: =IF(N5="50/30/20",B6*0.5,IF(N5="70/20/10",B6*0.7,0)) -> 0 | O6: 70/20/10 | Q6: Needs Actual | R6: =O15+O17+O19+O21 -> 0 | T6: Needs | U6: =C37 -> Savings | V6: =R6 -> 0 | X6: Needs
M7: Wants Target | N7: =IF(N5="50/30/20",B6*0.3,IF(N5="70/20/10",B6*0.2,0)) -> 0 | Q7: Wants Actual | R7: =O14+O16+O18+O20 -> 0 | X7: Wants
C8: (Follow the numbers below for easy of use) | M8: Savings Target | N8: =IF(N5="50/30/20",B6*0.2,IF(N5="70/20/10",B6*0.1,0)) -> 0 | Q8: Savings Actual | R8: =SUM(SavingsTbl_MonthlySpendingTemplate60710131619222528313437[Amount]) -> 0 | X8: Savings
Q9: Total Spent | R9: =R6+R7 -> 0
T11: Wants | U11: =C38 -> 401K | V11: =R11 -> 0
B12: 1. Income | E12: 2. Savings & Investments | I12: 4. Transactions Log | N12: Category Totals | T12: Savings | U12: =C39 -> Roth-IRA | V12: =R12 -> 0
B13: Source | C13: Amount | E13: Account | F13: Amount | I13: Date | J13: Category | K13: Amount | L13: Notes | N13: Category | O13: Total
N14: Subscriptions | O14: =SUMIFS(BillsTbl_MonthlySpendingTemplate5969121518212427303336[Actual],BillsTbl_MonthlySpendingTemplate5969121518212427303336[Category],"Subscriptions")+SUMIFS(K14:K72,J14:J72,"Subscriptions") -> 0 | Q14: want
N15: Gas | O15: =SUMIFS(BillsTbl_MonthlySpendingTemplate5969121518212427303336[Actual],BillsTbl_MonthlySpendingTemplate5969121518212427303336[Category],"Gas")+SUMIFS(K14:K72,J14:J72,"Gas") -> 0 | Q15: need
N16: Other | O16: =SUMIFS(BillsTbl_MonthlySpendingTemplate5969121518212427303336[Actual],BillsTbl_MonthlySpendingTemplate5969121518212427303336[Category],"Other")+SUMIFS(K14:K72,J14:J72,"Other") -> 0 | Q16: want
N17: Groceries | O17: =SUMIFS(BillsTbl_MonthlySpendingTemplate5969121518212427303336[Actual],BillsTbl_MonthlySpendingTemplate5969121518212427303336[Category],"Groceries")+SUMIFS(K14:K72,J14:J72,"Groceries") -> 0 | Q17: need
N18: Dining out | O18: =SUMIFS(BillsTbl_MonthlySpendingTemplate5969121518212427303336[Actual],BillsTbl_MonthlySpendingTemplate5969121518212427303336[Category],"Dining out")+SUMIFS(K14:K72,J14:J72,"Dining out") -> 0 | Q18: want
N19: Rent | O19: =SUMIFS(BillsTbl_MonthlySpendingTemplate5969121518212427303336[Actual],BillsTbl_MonthlySpendingTemplate5969121518212427303336[Category],"Rent")+SUMIFS(K14:K72,J14:J72,"Rent") -> 0 | Q19: need
N20: Shopping | O20: =SUMIFS(BillsTbl_MonthlySpendingTemplate5969121518212427303336[Actual],BillsTbl_MonthlySpendingTemplate5969121518212427303336[Category],"Shopping")+SUMIFS(K14:K72,J14:J72,"Shopping") -> 0 | Q20: want
B21: 3. Recurring Bills | N21: Credit Card | O21: =SUMIFS(BillsTbl_MonthlySpendingTemplate5969121518212427303336[Actual],BillsTbl_MonthlySpendingTemplate5969121518212427303336[Category],"Credit Card")+SUMIFS(K14:K72,J14:J72,"Credit Card") -> 0 | Q21: Need
B22: Bill Name | C22: Category | D22: Amount | E22: Paid? | F22: Actual
F23: =IF(E23=TRUE(),D23,0) -> 0
F24: =IF(E24=TRUE(),D24,0) -> 0
F25: =IF(E25=TRUE(),D25,0) -> 0
F26: =IF(E26=TRUE(),D26,0) -> 0
F27: =IF(E27=TRUE(),D27,0) -> 0
F28: =IF(E28=TRUE(),D28,0) -> 0
F29: =IF(E29=TRUE(),D29,0) -> 0
F30: =IF(E30=TRUE(),D30,0) -> 0
F31: =IF(E31=TRUE(),D31,0) -> 0
F32: =IF(E32=TRUE(),D32,0) -> 0
F33: =IF(E33=TRUE(),D33,0) -> 0
F34: =IF(E34=TRUE(),D34,0) -> 0
B36: Types of Saving/Investments
B37: 1 | C37: Savings
B38: 2 | C38: 401K
B39: 3 | C39: Roth-IRA
B40: 4 | C40: Brokerage

Sheet Dec
B1: MONTHLY BUDGET TEMPLATE
B5: Total Income | D5: Total Spent | F5: Leftover | H5: Savings Rate | J5: Bills Paid | M5: Budget Split | N5: 50/30/20 | O5: 50/30/20 | Q5: Spending Breakdown | U5: Budgeted | V5: Actual
B6: =SUM(IncomeTbl_MonthlySpendingTemplate575811141720232629323538[Amount]) -> 0 | D6: =R6+R11 -> 0 | F6: =B6-D6 -> 0 | H6: =IFERROR(R9/B6,0) -> 0 | J6: =COUNTIF(BillsTbl_MonthlySpendingTemplate596912151821242730333639[Paid?],TRUE())&" / "&COUNTA(BillsTbl_MonthlySpendingTemplate596912151821242730333639[Bill Name]) -> 0 / 0 | M6: Needs Target | N6: =IF(N5="50/30/20",B6*0.5,IF(N5="70/20/10",B6*0.7,0)) -> 0 | O6: 70/20/10 | Q6: Needs Actual | R6: =O15+O17+O19+O21 -> 0 | T6: Needs | U6: =C37 -> Savings | V6: =R6 -> 0 | X6: Needs
M7: Wants Target | N7: =IF(N5="50/30/20",B6*0.3,IF(N5="70/20/10",B6*0.2,0)) -> 0 | Q7: Wants Actual | R7: =O14+O16+O18+O20 -> 0 | X7: Wants
C8: (Follow the numbers below for easy of use) | M8: Savings Target | N8: =IF(N5="50/30/20",B6*0.2,IF(N5="70/20/10",B6*0.1,0)) -> 0 | Q8: Savings Actual | R8: =SUM(SavingsTbl_MonthlySpendingTemplate6071013161922252831343740[Amount]) -> 0 | X8: Savings
Q9: Total Spent | R9: =R6+R7 -> 0
T11: Wants | U11: =C38 -> 401K | V11: =R11 -> 0
B12: 1. Income | E12: 2. Savings & Investments | I12: 4. Transactions Log | N12: Category Totals | T12: Savings | U12: =C39 -> Roth-IRA | V12: =R12 -> 0
B13: Source | C13: Amount | E13: Account | F13: Amount | I13: Date | J13: Category | K13: Amount | L13: Notes | N13: Category | O13: Total
N14: Subscriptions | O14: =SUMIFS(BillsTbl_MonthlySpendingTemplate596912151821242730333639[Actual],BillsTbl_MonthlySpendingTemplate596912151821242730333639[Category],"Subscriptions")+SUMIFS(K14:K72,J14:J72,"Subscriptions") -> 0 | Q14: want
N15: Gas | O15: =SUMIFS(BillsTbl_MonthlySpendingTemplate596912151821242730333639[Actual],BillsTbl_MonthlySpendingTemplate596912151821242730333639[Category],"Gas")+SUMIFS(K14:K72,J14:J72,"Gas") -> 0 | Q15: need
N16: Other | O16: =SUMIFS(BillsTbl_MonthlySpendingTemplate596912151821242730333639[Actual],BillsTbl_MonthlySpendingTemplate596912151821242730333639[Category],"Other")+SUMIFS(K14:K72,J14:J72,"Other") -> 0 | Q16: want
N17: Groceries | O17: =SUMIFS(BillsTbl_MonthlySpendingTemplate596912151821242730333639[Actual],BillsTbl_MonthlySpendingTemplate596912151821242730333639[Category],"Groceries")+SUMIFS(K14:K72,J14:J72,"Groceries") -> 0 | Q17: need
N18: Dining out | O18: =SUMIFS(BillsTbl_MonthlySpendingTemplate596912151821242730333639[Actual],BillsTbl_MonthlySpendingTemplate596912151821242730333639[Category],"Dining out")+SUMIFS(K14:K72,J14:J72,"Dining out") -> 0 | Q18: want
N19: Rent | O19: =SUMIFS(BillsTbl_MonthlySpendingTemplate596912151821242730333639[Actual],BillsTbl_MonthlySpendingTemplate596912151821242730333639[Category],"Rent")+SUMIFS(K14:K72,J14:J72,"Rent") -> 0 | Q19: need
N20: Shopping | O20: =SUMIFS(BillsTbl_MonthlySpendingTemplate596912151821242730333639[Actual],BillsTbl_MonthlySpendingTemplate596912151821242730333639[Category],"Shopping")+SUMIFS(K14:K72,J14:J72,"Shopping") -> 0 | Q20: want
B21: 3. Recurring Bills | N21: Credit Card | O21: =SUMIFS(BillsTbl_MonthlySpendingTemplate596912151821242730333639[Actual],BillsTbl_MonthlySpendingTemplate596912151821242730333639[Category],"Credit Card")+SUMIFS(K14:K72,J14:J72,"Credit Card") -> 0 | Q21: Need
B22: Bill Name | C22: Category | D22: Amount | E22: Paid? | F22: Actual
F23: =IF(E23=TRUE(),D23,0) -> 0
F24: =IF(E24=TRUE(),D24,0) -> 0
F25: =IF(E25=TRUE(),D25,0) -> 0
F26: =IF(E26=TRUE(),D26,0) -> 0
F27: =IF(E27=TRUE(),D27,0) -> 0
F28: =IF(E28=TRUE(),D28,0) -> 0
F29: =IF(E29=TRUE(),D29,0) -> 0
F30: =IF(E30=TRUE(),D30,0) -> 0
F31: =IF(E31=TRUE(),D31,0) -> 0
F32: =IF(E32=TRUE(),D32,0) -> 0
F33: =IF(E33=TRUE(),D33,0) -> 0
F34: =IF(E34=TRUE(),D34,0) -> 0
B36: Types of Saving/Investments
B37: 1 | C37: Savings
B38: 2 | C38: 401K
B39: 3 | C39: Roth-IRA
B40: 4 | C40: Brokerage
